cloudlb
