Metadata-Version: 1.0
Name: python-cloudlb
Version: 0.5.1
Summary: Python interface to Rackspace Load Balancer as a Service product
Home-page: https://github.com/rackspace/python-cloudlb
Author: Chmouel Boudjnah
Author-email: chmouel@chmouel.com
License: MIT
Download-URL: https://github.com/rackspace/python-cloudlb/zipball/0.5.1
Platform: UNKNOWN
Classifier: Development Status :: 5 - Production/Stable
Classifier: Environment :: Console
Classifier: Intended Audience :: Developers
Classifier: License :: OSI Approved :: MIT License
Classifier: Programming Language :: Python
Classifier: Topic :: Internet :: WWW/HTTP
Classifier: Topic :: Software Development :: Libraries :: Python Modules
Classifier: Topic :: System :: Distributed Computing
Classifier: Topic :: Utilities
